scmcp/__init__.py
scmcp/cli.py
scmcp/server/__init__.py
scmcp-0.5.0.dist-info/METADATA
scmcp-0.5.0.dist-info/WHEEL
scmcp-0.5.0.dist-info/entry_points.txt
scmcp-0.5.0.dist-info/licenses/LICENSE
scmcp-0.5.0.dist-info/RECORD
