Metadata-Version: 2.4
Name: scmcp
Version: 0.5.0
Summary: An MCP server for scRNA-Seq analysis with natural language!
Project-URL: Homepage, http://scmcphub.org/
Project-URL: Repository, https://github.com/scmcphub/scmcp
Project-URL: Documentation, https://docs.scmcphub.org/
Author-email: shuang <hsh-me@outlook.com>
License: BSD 3-Clause License
License-File: LICENSE
Keywords: AI,agent,bioinformatics,llm,mcp,model context protocol,scRNA-seq,single cell
Requires-Python: >=3.10
Requires-Dist: agno
Requires-Dist: cellrank-mcp
Requires-Dist: decoupler-mcp
Requires-Dist: fastmcp>=2.10.0
Requires-Dist: infercnv-mcp
Requires-Dist: lancedb
Requires-Dist: liana-mcp
Requires-Dist: mcp>=1.8.0
Requires-Dist: nest-asyncio
Requires-Dist: scanpy-mcp
Requires-Dist: scmcp-shared>=0.6.0
